_
e
i
j
n
o
p
r
s
t
tests
