Metadata-Version: 1.1
Name: json-ptr
Version: 0.0.4
Summary: An implementation of IETF RFC 6901
Home-page: https://github.com/ermel272/json-ptr.git
Author: Chris Ermel
Author-email: ermel272@gmail.com
License: MIT
Keywords: JSON pointer IETF RFC 6901
Platform: UNKNOWN
Classifier: Development Status :: 2 - Pre-Alpha
Classifier: Intended Audience :: Developers
Classifier: Topic :: Software Development :: Libraries :: Python Modules
Classifier: License :: OSI Approved :: MIT License
Classifier: Programming Language :: Python :: 2.7
